pisense/__init__.py
pisense/anim.py
pisense/array.py
pisense/default.pbm
pisense/default.pil
pisense/easings.py
pisense/environ.py
pisense/exc.py
pisense/formats.py
pisense/imu.py
pisense/screen.py
pisense/settings.py
pisense/small.pbm
pisense/small.pil
pisense/stick.py
pisense-0.2.dist-info/METADATA
pisense-0.2.dist-info/RECORD
pisense-0.2.dist-info/WHEEL
pisense-0.2.dist-info/top_level.txt
