Metadata-Version: 2.1
Name: pisense
Version: 0.2
Summary: An alternative API for the Raspberry Pi Sense HAT
Home-page: http://pisense.readthedocs.io/
Author: Dave Jones
Author-email: dave@waveform.org.uk
License: BSD License
Keywords: raspberry,pi,sensehat
Platform: ALL
Classifier: Development Status :: 4 - Beta
Classifier: Environment :: Console
Classifier: Intended Audience :: Education
Classifier: Intended Audience :: Developers
Classifier: Topic :: Education
Classifier: Operating System :: POSIX :: Linux
Classifier: License :: OSI Approved :: BSD License
Classifier: Programming Language :: Python :: 2
Classifier: Programming Language :: Python :: 2.7
Classifier: Programming Language :: Python :: 3
Classifier: Programming Language :: Python :: 3.2
Classifier: Programming Language :: Python :: 3.3
Classifier: Programming Language :: Python :: 3.4
Classifier: Programming Language :: Python :: 3.5
Classifier: Programming Language :: Python :: 3.6
Classifier: Programming Language :: Python :: Implementation :: PyPy
Provides-Extra: doc
Provides-Extra: test
